{
    "coord": {
        "lon": 53.3518,
        "lat": -6.2614
    },
    "weather": [
        {
            "id": 804,
            "main": "Clouds",
            "description": "overcast clouds",
            "icon": "04d"
        }
    ],
    "base": "stations",
    "main": {
        "temp": 302.39,
        "feels_like": 307.45,
        "temp_min": 302.39,
        "temp_max": 302.39,
        "pressure": 1009,
        "humidity": 75,
        "sea_level": 1009,
        "grnd_level": 1009
    },
    "visibility": 10000,
    "wind": {
        "speed": 6.21,
        "deg": 289,
        "gust": 6.7
    },
    "clouds": {
        "all": 100
    },
    "dt": 1708427434,
    "sys": {
        "sunrise": 1708396332,
        "sunset": 1708440537
    },
    "timezone": 14400,
    "id": 0,
    "name": "",
    "cod": 200
}